quick_llama/__init__.py
quick_llama/manager.py
quick_llama-0.1.0.dist-info/licenses/LICENSE
quick_llama-0.1.0.dist-info/METADATA
quick_llama-0.1.0.dist-info/WHEEL
quick_llama-0.1.0.dist-info/top_level.txt
quick_llama-0.1.0.dist-info/RECORD
