Metadata-Version: 2.4
Name: quick-llama
Version: 0.1.0
Summary: Run Ollama models easily, anywhere – including online platforms like Google Colab
Home-page: https://github.com/nuhmanpk/quick-llama
Author: Nuhman PK
Project-URL: Documentation, https://github.com/nuhmanpk/quick-llama/blob/main/README.md
Project-URL: Funding, https://github.com/sponsors/nuhmanpk
Project-URL: Source, https://github.com/nuhmanpk/quick-llama/
Project-URL: Tracker, https://github.com/nuhmanpk/quick-llama/issues
Keywords: ollama llama3 colab ai open-source openai llm quick-llama
Classifier: Programming Language :: Python :: 3
Classifier: License :: OSI Approved :: MIT License
Classifier: Operating System :: OS Independent
Requires-Python: >=3.10
License-File: LICENSE
Requires-Dist: ollama
Requires-Dist: requests
Dynamic: author
Dynamic: classifier
Dynamic: description
Dynamic: description-content-type
Dynamic: home-page
Dynamic: keywords
Dynamic: license-file
Dynamic: project-url
Dynamic: requires-dist
Dynamic: requires-python
Dynamic: summary
